ppma/__init__.py
ppma/cam/__init__.py
ppma/cam/grad_cam.py
ppma/cam/utils.py
ppma/imagenet/__init__.py
ppma/imagenet/test.py
ppma/imagenet/utils.py
ppma/imagenet/validate.py
ppma/modelstat/__init__.py
ppma/modelstat/get_flops.py
ppma/modelstat/get_throughput.py
ppma/modelstat/op_count.py
ppma-1.1.1.dist-info/LICENSE
ppma-1.1.1.dist-info/METADATA
ppma-1.1.1.dist-info/WHEEL
ppma-1.1.1.dist-info/top_level.txt
ppma-1.1.1.dist-info/RECORD
