Metadata-Version: 2.1
Name: ppma
Version: 1.1.1
Summary: PaddlePaddle Model Analysis.
Home-page: https://github.com/lmk123568/Paddle_Model_Analysis
Author: Mike
Author-email: lmk123568@qq.com
License: MIT
Platform: UNKNOWN
Classifier: License :: OSI Approved :: MIT License
Classifier: Programming Language :: Python
Classifier: Programming Language :: Python :: 3
Classifier: Programming Language :: Python :: Implementation :: CPython
Classifier: Programming Language :: Python :: Implementation :: PyPy
Requires-Python: >=3.6.0
License-File: LICENSE
Requires-Dist: rich
Requires-Dist: opencv-python
